iehf.py
iehf-0.0.4.dist-info/METADATA
iehf-0.0.4.dist-info/WHEEL
iehf-0.0.4.dist-info/top_level.txt
iehf-0.0.4.dist-info/RECORD
