Metadata-Version: 2.1
Name: iehf
Version: 0.0.4
Summary: HF for IE
Home-page: UNKNOWN
Author: Ronkochu
License: UNKNOWN
Platform: UNKNOWN
Classifier: Programming Language :: Python :: 3
Classifier: License :: OSI Approved :: MIT License
Classifier: Operating System :: OS Independent
Requires-Python: >=3.6
Requires-Dist: numpy
Requires-Dist: inflect
Requires-Dist: scipy
